{
  "data_ref": "2025-12-20",
  "regulacao": [],
  "lancamentos_tecnologia": [
    {
      "titulo": "Working for a Great Firefighter Boss: Lessons from FDNY Veterans",
      "pais": "Resto LATAM",
      "link": "https://www.fireengineering.com/firefighting/working-for-a-great-firefighter-boss-lessons-from-fdny-veterans/"
    },
    {
      "titulo": "Man, Child Found Dead Inside Home in Overnight NY House Fire",
      "pais": "Resto LATAM",
      "link": "https://www.fireengineering.com/firefighting/structural-firefighting/man-child-found-dead-inside-home-in-overnight-ny-house-fire/"
    },
    {
      "titulo": "MN House Fire Leaves One Dead; Space Heater Suspected",
      "pais": "Resto LATAM",
      "link": "https://www.fireengineering.com/firefighting/mn-house-fire-leaves-one-dead-space-heater-suspected/"
    }
  ],
  "grandes_projetos": [],
  "score_paises": {
    "Resto LATAM": {
      "risco": 0,
      "oportunidade": 3
    }
  },
  "sumario_executivo": {
    "headline_dia": "Resumo automático diário do mercado de incêndio LATAM",
    "contexto": "Resumo gerado automaticamente a partir dos eventos coletados.",
    "acoes_recomendadas": [
      "Priorizar países com maior oportunidade",
      "Rever riscos regulatórios"
    ]
  }
}