{
  "data_ref": "2026-02-08",
  "regulacao": [],
  "lancamentos_tecnologia": [
    {
      "titulo": "Video Shows CT Firefighters Battle Fire That Displaced Four Residents",
      "pais": "Resto da América Latina",
      "link": "https://www.fireengineering.com/firefighting/video-shows-ct-firefighters-battle-fire-that-displaced-four-residents/"
    },
    {
      "titulo": "Three Fatalities, Three Injuries in OH Fire",
      "pais": "Resto da América Latina",
      "link": "https://www.fireengineering.com/firefighting/three-fatalities-three-injuries-in-oh-fire/"
    },
    {
      "titulo": "The Training Officer: Apparatus Positioning and Traffic Insights",
      "pais": "Resto da América Latina",
      "link": "https://www.fireengineering.com/fire-apparatus/the-training-officer-apparatus-positioning-and-traffic-insights/"
    },
    {
      "titulo": "Rescue Under Fire and Ice: NJ Firefighters Save Bedridden Resident from Residential Fire",
      "pais": "Resto da América Latina",
      "link": "https://www.fireengineering.com/firefighter-training/search-operations/rescue-under-fire-and-ice-maplewood-nj-fire/"
    },
    {
      "titulo": "The Single Source for Fire Service Training Guidance: The New NFPA 1400",
      "pais": "Resto da América Latina",
      "link": "https://www.fireengineering.com/firefighter-training/the-single-source-for-fire-service-training-guidance-the-new-nfpa-1400/"
    }
  ],
  "grandes_projetos": [],
  "score_paises": {
    "Resto da América Latina": {
      "risco": 0,
      "oportunidade": 5,
      "projects": 0,
      "market_size_usd": 360000000,
      "estimated_kidde_revenue_usd": 43200000
    },
    "Brasil": {
      "risco": 0,
      "oportunidade": 0,
      "projects": 0,
      "market_size_usd": 1200000000,
      "estimated_kidde_revenue_usd": 336000000
    },
    "Mexico": {
      "risco": 0,
      "oportunidade": 0,
      "projects": 0,
      "market_size_usd": 650000000,
      "estimated_kidde_revenue_usd": 143000000
    },
    "Colombia": {
      "risco": 0,
      "oportunidade": 0,
      "projects": 0,
      "market_size_usd": 220000000,
      "estimated_kidde_revenue_usd": 44000000
    },
    "Chile": {
      "risco": 0,
      "oportunidade": 0,
      "projects": 0,
      "market_size_usd": 180000000,
      "estimated_kidde_revenue_usd": 32400000
    },
    "Argentina": {
      "risco": 0,
      "oportunidade": 0,
      "projects": 0,
      "market_size_usd": 240000000,
      "estimated_kidde_revenue_usd": 40800000
    },
    "Peru": {
      "risco": 0,
      "oportunidade": 0,
      "projects": 0,
      "market_size_usd": 140000000,
      "estimated_kidde_revenue_usd": 21000000
    }
  },
  "sumario_executivo": {
    "headline_dia": "Resumo automático com base em dados públicos",
    "contexto": "Baseline público",
    "acoes_recomendadas": [
      "Priorizar países com maior pipeline",
      "Defender share onde Kidde é líder"
    ]
  }
}